gamspy_base/__init__.py
gamspy_base/eula.pdf
gamspy_base/gams
gamspy_base/gamscmex.out
gamspy_base/gamserrs.txt
gamspy_base/gamsgetkey
gamspy_base/gamslice.txt
gamspy_base/gamsprobe
gamspy_base/gamsstmp.txt
gamspy_base/gdxdiff
gamspy_base/gdxdump
gamspy_base/gevopt.def
gamspy_base/gmscmpun.txt
gamspy_base/gmscvnus.run
gamspy_base/gmscvnux.out
gamspy_base/gmsgenus.run
gamspy_base/gmsgenux.out
gamspy_base/gmske_us.run
gamspy_base/gmske_ux.out
gamspy_base/gmsprmun.txt
gamspy_base/gmssb_us.run
gamspy_base/gmssb_ux.out
gamspy_base/libco4cclib64.dylib
gamspy_base/libconopt464.dylib
gamspy_base/libconoptlu.dylib
gamspy_base/libcplex2212.dylib
gamspy_base/libcpxcclib64.dylib
gamspy_base/libcrypto.3.dylib
gamspy_base/libcvdcclib64.dylib
gamspy_base/libdctmdclib64.dylib
gamspy_base/libgcc_s.1.1.dylib
gamspy_base/libgdxcclib64.dylib
gamspy_base/libgdxdclib64.dylib
gamspy_base/libgfortran.5.dylib
gamspy_base/libgmdcclib64.dylib
gamspy_base/libgmszlib164.dylib
gamspy_base/libgomp.1.dylib
gamspy_base/libgsscclib64.dylib
gamspy_base/libguccclib64.dylib
gamspy_base/libjoatdclib64.dylib
gamspy_base/liboptdclib64.dylib
gamspy_base/libpath52.dylib
gamspy_base/libptccclib64.dylib
gamspy_base/libquadmath.0.dylib
gamspy_base/libssl.3.dylib
gamspy_base/libstdc++.6.dylib
gamspy_base/mps2gms
gamspy_base/optconopt.def
gamspy_base/optconvert.def
gamspy_base/optcplex.def
gamspy_base/optgams.def
gamspy_base/optnlpec.def
gamspy_base/optpath.def
gamspy_base/optsbb.def
gamspy_base/version.py
minigams-env-3.1268412939/lib/python3.12/site-packages/minigams/GAMSPY_BASE_README.md
gamspy_base-52.4.0.dist-info/METADATA
gamspy_base-52.4.0.dist-info/WHEEL
gamspy_base-52.4.0.dist-info/top_level.txt
gamspy_base-52.4.0.dist-info/RECORD
