Metadata-Version: 2.4
Name: gamspy_base
Version: 52.4.0
Requires-Dist: gamspy_arm_perf==52.4.0
Dynamic: description
Dynamic: description-content-type
Dynamic: requires-dist
